instagram_to_discord/__init__.py
instagram_to_discord-0.1.4.dist-info/LICENSE
instagram_to_discord-0.1.4.dist-info/METADATA
instagram_to_discord-0.1.4.dist-info/WHEEL
instagram_to_discord-0.1.4.dist-info/top_level.txt
instagram_to_discord-0.1.4.dist-info/RECORD
