Metadata-Version: 2.1
Name: instagram-to-discord
Version: 0.1.4
Summary: Integrate instagram to discord
Home-page: https://github.com/jd-apprentice/instagram-to-discord
Author: jd-apprentice
Author-email: contacto@jonathan.com.ar
Classifier: Programming Language :: Python :: 3
Classifier: License :: OSI Approved :: GNU General Public License v3 (GPLv3)
Classifier: Operating System :: OS Independent
Requires-Python: >=3.6
License-File: LICENSE
